{
    "id": 153002,
    "old_rating": "4.66667",
    "comments": "0",
    "favorites": "0",
    "likes": "0",
    "myfcm_type": "0",
    "ing": [
        "1 tray ice cubes",
        "6 fluid ounces jagermeister liqueur",
        "6 fluid ounces coconut-flavored rum",
        "2 1/2 cups pineapple juice",
        "1 orange slice (optional)"
    ],
    "nut": [],
    "n": "California Surfer",
    "a": "Kevin",
    "r": "0",
    "s": 5,
    "des": "\"Close your eyes and imagine being in sunny California with this great drink. Perfect for chilling down with on a hot summer day. Surf's up!\"",
    "ins": "Fill a pitcher with ice cubes. Pour the jagermeister, coconut rum and pineapple juice over the ice.  Stir and garnish with a slice of orange.",
    "pt": "5 m",
    "ct": "",
    "tt": "",
    "i": "287037.jpg",
    "o": "",
    "st": "allrecipes"
}