{
    "id": 156468,
    "old_rating": "5",
    "comments": "0",
    "favorites": "0",
    "likes": "0",
    "myfcm_type": "1",
    "ing": [
        "ice",
        "1 fluid ounce orange vodka",
        "1 fluid ounce raspberry vodka",
        "1/2 fluid ounce coconut-flavored rum",
        "2 fluid ounces orange juice",
        "2 fluid ounces pineapple juice",
        "1 dash grenadine",
        "1 orange wedge, for garnish"
    ],
    "nut": [],
    "n": "Caribbean Breeze",
    "a": "Marcy",
    "r": "0",
    "s": 1,
    "des": "\"This is a refreshing, fruity cocktail.\"",
    "ins": "Fill a tall glass with ice. Pour the orange vodka, raspberry vodka, rum, orange juice, pineapple juice, and grenadine over the ice; stir well. Garnish with an orange wedge.",
    "pt": "5 m",
    "ct": "",
    "tt": "",
    "i": "1379039.jpg",
    "o": "",
    "st": "allrecipes"
}