{
    "id": 18972,
    "old_rating": "3",
    "comments": "0",
    "favorites": "0",
    "likes": "0",
    "myfcm_type": "0",
    "ing": [
        "2 fluid ounces absinthe",
        "2 fluid ounces water",
        "2 fluid ounces sour mix",
        "2 cubes  white sugar"
    ],
    "nut": [],
    "n": "Soursinth",
    "a": "Joey",
    "r": "0",
    "s": 1,
    "des": "\"Great and tasteful chilled drink for the spirits, made with absinthe and sour mix.\"",
    "ins": "Chill the absinthe glass, a spoon and the absinthe in the freezer for at least four hours. Chill water in refrigerator.\nSet the spoon upon the chilled absinthe glass. Place the sugar cubes on the spoon. Pour absinthe over the sugar cubes. Pour chilled water over sugar cubes. Pour sour mix over remainder of sugar cubes. If any sugar is left on spoon, dump it into the glass and stir.",
    "pt": "4 h",
    "ct": "5 m",
    "tt": "4 h ",
    "i": "1939218.jpg",
    "o": "",
    "st": "allrecipes"
}