{
    "id": 19161,
    "old_rating": "4.66667",
    "comments": "0",
    "favorites": "0",
    "likes": "0",
    "myfcm_type": "0",
    "ing": [
        "7 cups water",
        "2 pints lemon gin",
        "1 cup cold tea",
        "1 (12 fluid ounce) can frozen lemonade concentrate",
        "1 (12 fluid ounce) can frozen orange juice concentrate",
        "1/2 cup white sugar",
        "2 liters lemon-lime flavored carbonated beverage"
    ],
    "nut": [],
    "n": "Lemon Gin Slush",
    "a": "mmurphy",
    "r": "0",
    "s": 10,
    "des": "\"A frozen drink from heaven! This drink will keep your friends happy and in the mood for fun all afternoon!\"",
    "ins": "In a mixing bowl, combine water, gin, tea, frozen lemonade, frozen orange juice, and sugar. Mix well and store in the freezer (covered) until ready to use.\nTo serve: in a tall glass combine frozen mixture to taste with lemon-lime flavored carbonated beverage.",
    "pt": "5 m",
    "ct": "",
    "tt": "",
    "i": "359309.jpg",
    "o": "",
    "st": "allrecipes"
}