{
    "id": 20025,
    "old_rating": "4.18",
    "comments": "0",
    "favorites": "0",
    "likes": "0",
    "myfcm_type": "1",
    "ing": [
        "2 cups limeade prepared from concentrate",
        "1/2 cup pineapple juice",
        "1/2 cup orange juice",
        "2 fluid ounces tequila",
        "1 fluid ounce orange liqueur"
    ],
    "nut": [],
    "n": "A Fantastic Margarita",
    "a": "THEATREGIRL",
    "r": "0",
    "s": 2,
    "des": "\"My husband was a bartender for a trendy restaurant when we met.  Here's one of his home versions! Garnish with a lime wedge or an orange wedge.\"",
    "ins": "Salt the rims of 2 large margarita glasses. To do so, pour salt onto a small plate, moisten the rims of the glasses on a damp towel and press them into the salt.\nIn a pitcher combine limeade, pineapple juice, orange juice, tequila and orange liqueur. Stir well and pour into the glasses, being careful not to rinse off the salt.",
    "pt": "3 m",
    "ct": "",
    "tt": "",
    "i": "3657559.jpg",
    "o": "",
    "st": "allrecipes"
}