{
    "id": 20145,
    "old_rating": "4.71429",
    "comments": "0",
    "favorites": "0",
    "likes": "0",
    "myfcm_type": "1",
    "ing": [
        "1 (1.5 fluid ounce) jigger vodka",
        "1/2 cup caffeinated citrus-flavored soda",
        "1 dash dry vermouth"
    ],
    "nut": [],
    "n": "Eighty-Six Benevolent Street",
    "a": "Courtney",
    "r": "0",
    "s": 1,
    "des": "\"This wildly colored drink was named after the address where my housemates and I were staying when we created it.\"",
    "ins": "Fill a tall glass with ice cubes. Pour in the vodka and citrus soda. Splash on the vermouth. Stir and serve.",
    "pt": "2 m",
    "ct": "",
    "tt": "",
    "i": "29071.jpg",
    "o": "",
    "st": "allrecipes"
}