{
    "id": 20626,
    "old_rating": "4.6",
    "comments": "0",
    "favorites": "0",
    "likes": "0",
    "myfcm_type": "0",
    "ing": [
        "1 (1.5 fluid ounce) jigger gin",
        "1 (1.5 fluid ounce) jigger triple sec liqueur",
        "1/2 fluid ounce peach schnapps",
        "2 fluid ounces orange juice",
        "2 fluid ounces lemon-lime flavored carbonated beverage",
        "1 dash grenadine syrup"
    ],
    "nut": [],
    "n": "Golden Rays of Peach Delight",
    "a": "Karla Flynn",
    "r": "0",
    "s": 1,
    "des": "\"Very fresh and tasty alcoholic drink with an peachy-orange twist! Watch out and be sure to sip slowly - not for the faint-hearted!!!\"",
    "ins": "Fill a tall glass with ice. Pour in the gin, triple sec, peach schnapps and orange juice. Fill the glass with lemon-lime soda and finish with a dash of grenadine. Stir and serve.",
    "pt": "2 m",
    "ct": "",
    "tt": "",
    "i": "72365.jpg",
    "o": "",
    "st": "allrecipes"
}