{
    "id": 217299,
    "old_rating": "4.42857",
    "comments": "0",
    "favorites": "0",
    "likes": "0",
    "myfcm_type": "0",
    "ing": [
        "2 bunches baby red or gold beets",
        "1 medium fennel bulb",
        "1 (5 ounce) package DOLE\u00c2\u00ae Spring Mix",
        "1 (15 ounce) can DOLE\u00c2\u00ae Mandarin Oranges, drained",
        "4 sprigs fresh mint, chopped",
        "1/2 cup shallot vinaigrette (recipe below)",
        "1/2 cup crumbled goat cheese"
    ],
    "nut": [],
    "n": "Beet, Fennel and Mandarin Orange Salad",
    "a": "Dole",
    "r": "0",
    "s": 4,
    "des": "\"Roasted beets and sweet oranges are dressed with a sherry-shallot vinaigrette in this flavorful salad.\"",
    "ins": "Preheat oven to 400 degrees F.\nPlace beets in medium roasting pan, add water to cover bottom of pan; cover with foil. Roast 40 to 45 minutes or until beets are tender and can be pierced with a fork or knife.\nCool slightly; remove skin from beets and cut into wedges.\nTrim off fennel leaves and stalk; cut into very thin slices.\nCombine salad, mandarin oranges, mint, beets and fennel in large bowl. Pour dressing over salad; toss to evenly coat.\nSprinkle cheese over salad.",
    "pt": "20 m",
    "ct": "",
    "tt": "",
    "i": "980609.jpg",
    "o": "",
    "st": "allrecipes"
}