{
    "id": 22361,
    "old_rating": "4.33333",
    "comments": "0",
    "favorites": "0",
    "likes": "0",
    "myfcm_type": "1",
    "ing": [
        "2 fluid ounces Southern Comfort",
        "2 fluid ounces cinnamon schnapps",
        "4 fluid ounces cola-flavored carbonated beverage"
    ],
    "nut": [],
    "n": "Angry Dan",
    "a": "Dan",
    "r": "0",
    "s": 1,
    "des": "\"HEY! Don't drink too many of these! Southern Comfort and cinnamon schnapps mixed with cola.\"",
    "ins": "In a glass full of ice, pour Southern Comfort and cinnamon schnapps. Fill glass with Cola.",
    "pt": "1 m",
    "ct": "",
    "tt": "",
    "i": "235516.jpg",
    "o": "",
    "st": "allrecipes"
}