{
    "id": 229406,
    "old_rating": "3.6",
    "comments": "0",
    "favorites": "0",
    "likes": "0",
    "myfcm_type": "0",
    "ing": [
        "24 Winter OREO Cookies, divided",
        "3 tablespoons cream cheese, softened",
        "9 ounces white chocolate, melted",
        "Assorted colored decorating gels"
    ],
    "nut": [],
    "n": "Melting Snowmen OREO Cookie Balls",
    "a": "Oreo",
    "r": "0",
    "s": 15,
    "des": "\"Cold weather got you down? Bring the outdoors in with these cool confections, sure to make a winter lover out of everyone.\"",
    "ins": "Crush 9 cookies finely; mix with cream cheese until blended. Shape into 15 balls.\nPlace remaining cookies on waxed paper-covered rimmed baking sheet. Dip balls in chocolate; place on cookies. Tap cookies on baking sheet several times to allow excess chocolate to pool onto tops of cookies. Decorate with gels to resemble snowmen.\nRefrigerate 1 hour or until firm.",
    "pt": "30 m",
    "ct": "",
    "tt": "",
    "i": "988279.jpg",
    "o": "",
    "st": "allrecipes"
}